MingxiangWufenzhong/Dockerfile
MingxiangWufenzhong/README.md
MingxiangWufenzhong/__init__.py
MingxiangWufenzhong/__main__.py
MingxiangWufenzhong/file.epub
MingxiangWufenzhong/index.html
MingxiangWufenzhong/css/__init__.py
MingxiangWufenzhong/css/annotations.css
MingxiangWufenzhong/css/main.css
MingxiangWufenzhong/css/normalize.css
MingxiangWufenzhong/css/popup.css
MingxiangWufenzhong/font/__init__.py
MingxiangWufenzhong/font/fontello.eot
MingxiangWufenzhong/font/fontello.svg
MingxiangWufenzhong/font/fontello.ttf
MingxiangWufenzhong/font/fontello.woff
MingxiangWufenzhong/img/__init__.py
MingxiangWufenzhong/img/annotator-glyph-sprite.png
MingxiangWufenzhong/img/annotator-icon-sprite.png
MingxiangWufenzhong/img/apple-touch-icon.png
MingxiangWufenzhong/img/cancelfullscreen.png
MingxiangWufenzhong/img/close.png
MingxiangWufenzhong/img/fullscreen.png
MingxiangWufenzhong/img/loader.gif
MingxiangWufenzhong/img/menu-icon.png
MingxiangWufenzhong/img/save.png
MingxiangWufenzhong/img/saved.png
MingxiangWufenzhong/img/settings-s.png
MingxiangWufenzhong/img/settings.png
MingxiangWufenzhong/img/star.png
MingxiangWufenzhong/js/__init__.py
MingxiangWufenzhong/js/epub.js
MingxiangWufenzhong/js/epub.min.js
MingxiangWufenzhong/js/epub.min.map
MingxiangWufenzhong/js/hooks.min.js
MingxiangWufenzhong/js/hooks.min.map
MingxiangWufenzhong/js/reader.js
MingxiangWufenzhong/js/reader.js.map
MingxiangWufenzhong/js/reader.min.js
MingxiangWufenzhong/js/reader.min.map
MingxiangWufenzhong/js/hooks/__init__.py
MingxiangWufenzhong/js/hooks/extensions/__init__.py
MingxiangWufenzhong/js/hooks/extensions/highlight.js
MingxiangWufenzhong/js/libs/__init__.py
MingxiangWufenzhong/js/libs/jquery.min.js
MingxiangWufenzhong/js/libs/localforage.min.js
MingxiangWufenzhong/js/libs/screenfull.js
MingxiangWufenzhong/js/libs/screenfull.min.js
MingxiangWufenzhong/js/libs/zip.min.js
MingxiangWufenzhong/js/plugins/__init__.py
MingxiangWufenzhong/js/plugins/hypothesis.js
MingxiangWufenzhong/js/plugins/search.js
mingxiang_wufenzhong-2022.10.9.1.dist-info/METADATA
mingxiang_wufenzhong-2022.10.9.1.dist-info/WHEEL
mingxiang_wufenzhong-2022.10.9.1.dist-info/entry_points.txt
mingxiang_wufenzhong-2022.10.9.1.dist-info/top_level.txt
mingxiang_wufenzhong-2022.10.9.1.dist-info/RECORD
